langgraph_tracer/__init__.py
langgraph_tracer/agent_executor.py
langgraph_tracer/chat_agent_executor_with_function_calling.py
langgraph_tracer/stateGraphWork.py
langgraph_tracer/test-trace.py
langgraph_tracer-1.0.4.dist-info/LICENSE
langgraph_tracer-1.0.4.dist-info/METADATA
langgraph_tracer-1.0.4.dist-info/WHEEL
langgraph_tracer-1.0.4.dist-info/top_level.txt
langgraph_tracer-1.0.4.dist-info/RECORD
